README.md
setup.py
pysimilarity/__init__.py
pysimilarity/base.py
pysimilarity/classifier.py
pysimilarity/distance.py
pysimilarity.egg-info/PKG-INFO
pysimilarity.egg-info/SOURCES.txt
pysimilarity.egg-info/dependency_links.txt
pysimilarity.egg-info/requires.txt
pysimilarity.egg-info/top_level.txt
pysimilarity/__pycache__/__init__.cpython-37.pyc
pysimilarity/__pycache__/base.cpython-37.pyc
pysimilarity/__pycache__/classifier.cpython-37.pyc
pysimilarity/__pycache__/distance.cpython-37.pyc