Metadata-Version: 2.1
Name: pysimilarity
Version: 0.1.0
Summary: Determine similarity between datasets
Home-page: https://github.com/JuanCorp/pysimilarity
Author: JuanCorp
Author-email: juan.nunez.corp@gmail.com
License: UNKNOWN
Keywords: similarity data machine learning
Platform: UNKNOWN
Classifier: Development Status :: 3 - Alpha
Classifier: Intended Audience :: Developers
Classifier: Topic :: Scientific/Engineering :: Artificial Intelligence
Classifier: License :: OSI Approved :: MIT License
Classifier: Programming Language :: Python :: 3.6
Classifier: Programming Language :: Python :: 3.7
Requires-Python: >=3, <4
